xopt/__init__.py
xopt/__main__.py
xopt/cli.py
xopt/client.py
xopt/decorators.py
xopt/instance.py
xopt/llm.py
xopt/models.py
xopt/registry.py
xopt/runner.py
xopt/utils.py
xoptpy-0.1.1.dist-info/LICENSE
xoptpy-0.1.1.dist-info/METADATA
xoptpy-0.1.1.dist-info/WHEEL
xoptpy-0.1.1.dist-info/entry_points.txt
xoptpy-0.1.1.dist-info/RECORD
