Metadata-Version: 2.3
Name: xoptpy
Version: 0.1.1
Summary: eXtreme OPTimization - More optimizing agentic AI
Keywords: optimization,ai,agentic,llm,agents
Author: Jake Derry
Requires-Python: >=3.9,<3.14
Classifier: Development Status :: 3 - Alpha
Classifier: Intended Audience :: Developers
Classifier: Intended Audience :: Science/Research
Classifier: License :: OSI Approved :: MIT License
Classifier: Operating System :: OS Independent
Classifier: Programming Language :: Python :: 3
Classifier: Programming Language :: Python :: 3.9
Classifier: Programming Language :: Python :: 3.10
Classifier: Programming Language :: Python :: 3.11
Classifier: Programming Language :: Python :: 3.12
Classifier: Programming Language :: Python :: 3.13
Classifier: Programming Language :: Python :: 3.8
Classifier: Topic :: Scientific/Engineering :: Artificial Intelligence
Classifier: Topic :: Software Development :: Libraries :: Python Modules
Provides-Extra: all
Provides-Extra: anthropic
Provides-Extra: docs
Provides-Extra: dspy
Provides-Extra: embeddings
Provides-Extra: langgraph
Provides-Extra: llm
Provides-Extra: mlflow
Provides-Extra: numpy
Provides-Extra: ollama
Provides-Extra: openai
Provides-Extra: pandas
Provides-Extra: web
Requires-Dist: beautifulsoup4 (>=4.11.0,<5.0.0) ; extra == "web" or extra == "all"
Requires-Dist: click (>=8.1.0,<9.0.0)
Requires-Dist: dspy (>=2.4.0,<3.0.0) ; extra == "dspy" or extra == "all"
Requires-Dist: faiss-cpu (>=1.7.4,<2.0.0) ; extra == "embeddings" or extra == "all"
Requires-Dist: fastapi (>=0.104.0,<0.105.0)
Requires-Dist: langchain (>=0.2.0,<0.3.0) ; extra == "llm" or extra == "all"
Requires-Dist: langchain-anthropic (>=0.1.0,<0.2.0) ; extra == "anthropic" or extra == "llm" or extra == "all"
Requires-Dist: langchain-core (>=0.2.0,<0.3.0) ; extra == "llm" or extra == "all"
Requires-Dist: langchain-ollama (>=0.1.0,<0.2.0) ; extra == "ollama" or extra == "llm"
Requires-Dist: langchain-openai (>=0.1.0,<0.2.0) ; extra == "openai" or extra == "llm" or extra == "all"
Requires-Dist: langgraph (>=0.2.0,<0.3.0) ; extra == "langgraph" or extra == "all"
Requires-Dist: litellm (>=1.74.9,<2.0.0)
Requires-Dist: mlflow (>=2.0.0,<3.0.0) ; extra == "mlflow" or extra == "all"
Requires-Dist: numpy (>=1.21.0,<2.0.0) ; extra == "numpy" or extra == "pandas" or extra == "mlflow" or extra == "embeddings" or extra == "all"
Requires-Dist: pandas (>=2.1.0,<3.0.0) ; extra == "pandas" or extra == "mlflow" or extra == "all"
Requires-Dist: pydantic (>=2.0.0,<3.0.0)
Requires-Dist: pypdf2 (>=3.0.0,<4.0.0) ; extra == "docs" or extra == "all"
Requires-Dist: python-docx (>=0.8.11,<0.9.0) ; extra == "docs" or extra == "all"
Requires-Dist: pyyaml (>=6.0.0,<7.0.0)
Requires-Dist: requests (>=2.31.0,<3.0.0) ; extra == "web" or extra == "all"
Requires-Dist: sentence-transformers (>=2.2.0,<3.0.0) ; extra == "embeddings" or extra == "all"
Requires-Dist: toml (>=0.10.2,<0.11.0)
Requires-Dist: uvicorn (>=0.24.0,<0.25.0)
Project-URL: Documentation, https://docs.xopt.ai
Project-URL: Homepage, https://github.com/x-opt/xoptpy
Project-URL: Repository, https://github.com/x-opt/xoptpy
